Workbook

Sheet EDT
A2: EDT - Planilla Estructura de Descomposición de Tareas — FitSearch
A3: Capstone PTY4614, sección 003D · Equipo: Rodrigo Cárcamo Rojas, Luis Méndez y Nicolás Silva · Estimación en horas-hombre (HH) al 03-10-2026
A4: ACTIVIDADES | C4: Horas por Actividad o entregable | J4: DICCIONARIO EDT
A5: Fase Análisis y Planificación (Fase 1, semanas 1 a 4) | B5: Días | C5: JP | D5: AF | E5: PG | F5: DBA | G5: TS | H5: DI | J5: SIGLA | K5: ROL | L5: NOMBRE | M5: COSTO x HORA
A6: Kick off y conformación del equipo Scrum (roles y acuerdos de trabajo) | B6: 0.5 | C6: 2 | D6: 2 | E6: 2 | J6: JP | K6: JEFE DE PROYECTO (SCRUM MASTER) | L6: Luis Méndez | M6: ='ANALISIS INGRESOS'!G6
A7: Definición del problema, objetivos y visión del producto (Product Vision) | B7: 1 | C7: 2 | D7: 8 | J7: AF | K7: ANALISTA FUNCIONAL (PRODUCT OWNER) | L7: Rodrigo Cárcamo Rojas | M7: ='ANALISIS INGRESOS'!G7
A8: Épicas e historias de usuario con criterios de aceptación | B8: 1 | C8: 2 | D8: 10 | E8: 2 | J8: PG | K8: PROGRAMADOR | L8: Rodrigo Cárcamo Rojas, Luis Méndez y Nicolás Silva | M8: ='ANALISIS INGRESOS'!G8
A9: Estimación (Planning Poker) y priorización del Product Backlog | B9: 0.5 | C9: 2 | D9: 2 | E9: 2 | J9: DBA | K9: ADMIN. BASE DATOS | L9: Luis Méndez y Rodrigo Cárcamo Rojas | M9: ='ANALISIS INGRESOS'!G9
A10: Plan de trabajo, Carta Gantt y hoja de ruta | B10: 0.5 | C10: 6 | D10: 2 | J10: TS | K10: TESTING | L10: Equipo completo (cada responsable prueba su historia) | M10: ='ANALISIS INGRESOS'!G10
A11: Guía de la Fase 1 (Definición del Proyecto APT) | B11: 1 | C11: 3 | D11: 4 | E11: 2 | J11: DI | K11: DISEÑADOR | L11: Nicolás Silva (interfaz) y Rodrigo Cárcamo Rojas (mockups) | M11: ='ANALISIS INGRESOS'!G11
A12: Presentación de la Fase 1 y aprobación del proyecto | B12: 0.5 | C12: 2 | D12: 2 | E12: 2 | H12: 2
A13: Fase Diseño (Fase 2, semanas 5 a 9, en paralelo con los sprints) | B13: Días | C13: JP | D13: AF | E13: PG | F13: DBA | G13: TS | H13: DI
A14: Refinamiento del backlog y análisis de los requerimientos nuevos (13 historias agregadas) | B14: 1 | C14: 2 | D14: 12 | L14: COSTO POR FASE
A15: Diagramas UML del modelo 4+1 en Miro (casos de uso, clases, secuencia, componentes y despliegue) | B15: 1 | C15: 2 | D15: 4 | E15: 8 | L15: Fase Análisis y Planificación | M15: =SUM(C6:C12)*$M$6+SUM(D6:D12)*$M$7+SUM(E6:E12)*$M$8+SUM(F6:F12)*$M$9+SUM(G6:G12)*$M$10+SUM(H6:H12)*$M$11
A16: Modelo de datos, diccionario y diagrama entidad-relación (14 tablas) | B16: 1 | D16: 2 | F16: 8 | L16: Fase Diseño | M16: =SUM(C14:C20)*$M$6+SUM(D14:D20)*$M$7+SUM(E14:E20)*$M$8+SUM(F14:F20)*$M$9+SUM(G14:G20)*$M$10+SUM(H14:H20)*$M$11
A17: Documento de Arquitectura del Sistema (DAS): decisiones de diseño y escenarios de calidad | B17: 1.5 | C17: 2 | D17: 4 | E17: 8 | F17: 2 | L17: Fase de Desarrollo | M17: =SUM(C22:C55)*$M$6+SUM(D22:D55)*$M$7+SUM(E22:E55)*$M$8+SUM(F22:F55)*$M$9+SUM(G22:G55)*$M$10+SUM(H22:H55)*$M$11
A18: Diseño de interfaz: identidad visual (logo y paleta) y mockups de pantallas | B18: 1.5 | D18: 4 | H18: 16 | L18: Fase Implementación y Cierre | M18: =SUM(C57:C63)*$M$6+SUM(D57:D63)*$M$7+SUM(E57:E63)*$M$8+SUM(F57:F63)*$M$9+SUM(G57:G63)*$M$10+SUM(H57:H63)*$M$11
A19: Definition of Done (acuerdo y aprobación del equipo) | B19: 0.5 | C19: 2 | D19: 2 | E19: 2 | L19: Total costo HH del proyecto | M19: =SUM(M15:M18)
A20: Plan de pruebas y planilla de casos de prueba | B20: 1 | D20: 2 | G20: 8
A21: Fase de Desarrollo (Fase 2, Sprints 1 a 5, semanas 5 a 15) | B21: Días | C21: JP | D21: AF | E21: PG | F21: DBA | G21: TS | H21: DI | L21: COSTO HH POR ROL
A22: Implementación del ambiente de desarrollo (GitHub con rama main protegida, Node.js, React + Vite, MySQL 8 y Prisma) | B22: 0.5 | C22: 1 | E22: 3 | F22: 2 | L22: JEFE DE PROYECTO (SCRUM MASTER) | M22: =C65*$M$6
A23: Ceremonias Scrum de los 5 sprints (planificación, revisión y retrospectiva) | B23: 4.5 | C23: 20 | D23: 15 | E23: 20 | L23: ANALISTA FUNCIONAL (PRODUCT OWNER) | M23: =D65*$M$7
A24: Revisión de código, pull requests y aceptación del Product Owner (DoD) | B24: 3 | D24: 12 | E24: 23 | L24: PROGRAMADOR | M24: =E65*$M$8
A25: E1 Gestión de usuarios | L25: ADMIN. BASE DATOS | M25: =F65*$M$9
A26: FS-HU-01 Registro y login (Sprint 1, horas reales) | B26: 2 | E26: 17 | G26: 5 | L26: TESTING | M26: =G65*$M$10
A27: FS-HU-02 Datos básicos del perfil (Sprint 1, horas reales) | B27: 2 | E27: 9 | F27: 10 | G27: 2 | L27: DISEÑADOR | M27: =H65*$M$11
A28: FS-HU-15 Recuperar contraseña (Sprint 2) | B28: 2 | D28: 1 | E28: 15 | F28: 4 | G28: 4 | H28: 3 | L28: TOTAL HH | M28: =SUM(M22:M27)
A29: FS-HU-16 Acceso con Google (Sprint 2) | B29: 2 | D29: 3 | E29: 16 | F29: 1 | G29: 5 | H29: 2 | L29: Total horas-hombre del proyecto | M29: =SUM(C65:H65)
A30: FS-HU-17 Registro con contraseña confirmada y sesión recordada (Sprint 2) | B30: 1.5 | D30: 1 | E30: 9 | F30: 2 | G30: 2 | H30: 2
A31: FS-HU-18 Objetivos y estilo de vida (Sprint 2) | B31: 1.5 | D31: 1 | E31: 9 | F31: 2 | G31: 2 | H31: 2 | L31: COSTO POR COMPONENTE CODIFICACION
A32: FS-HU-19 Información de salud (Sprint 2) | B32: 2 | D32: 1 | E32: 15 | F32: 4 | G32: 4 | H32: 3 | L32: E1 Gestión de usuarios | M32: =SUM(C26:C34)*$M$6+SUM(D26:D34)*$M$7+SUM(E26:E34)*$M$8+SUM(F26:F34)*$M$9+SUM(G26:G34)*$M$10+SUM(H26:H34)*$M$11
A33: FS-HU-20 Portada pública (Sprint 2) | B33: 1 | D33: 1 | E33: 5 | G33: 2 | H33: 3 | L33: E2 Profesionales | M33: =SUM(C36:C40)*$M$6+SUM(D36:D40)*$M$7+SUM(E36:E40)*$M$8+SUM(F36:F40)*$M$9+SUM(G36:G40)*$M$10+SUM(H36:H40)*$M$11
A34: FS-HU-21 Inicio personalizado y navegación (Sprint 3) | B34: 2 | D34: 1 | E34: 14 | G34: 4 | H34: 8 | L34: E3 Búsqueda geolocalizada | M34: =SUM(C42:C44)*$M$6+SUM(D42:D44)*$M$7+SUM(E42:E44)*$M$8+SUM(F42:F44)*$M$9+SUM(G42:G44)*$M$10+SUM(H42:H44)*$M$11
A35: E2 Profesionales | L35: E4 Asistente de inteligencia artificial | M35: =SUM(C46:C47)*$M$6+SUM(D46:D47)*$M$7+SUM(E46:E47)*$M$8+SUM(F46:F47)*$M$9+SUM(G46:G47)*$M$10+SUM(H46:H47)*$M$11
A36: FS-HU-03 Listado de profesionales (Sprint 2) | B36: 2 | D36: 1 | E36: 15 | F36: 4 | G36: 4 | H36: 3 | L36: E5 Gestor de alimentación | M36: =SUM(C49:C50)*$M$6+SUM(D49:D50)*$M$7+SUM(E49:E50)*$M$8+SUM(F49:F50)*$M$9+SUM(G49:G50)*$M$10+SUM(H49:H50)*$M$11
A37: FS-HU-04 Perfil de profesional (Sprint 2) | B37: 2 | D37: 1 | E37: 15 | F37: 4 | G37: 4 | H37: 3 | L37: E6 Infraestructura | M37: =SUM(C52:C52)*$M$6+SUM(D52:D52)*$M$7+SUM(E52:E52)*$M$8+SUM(F52:F52)*$M$9+SUM(G52:G52)*$M$10+SUM(H52:H52)*$M$11
A38: FS-HU-12 Verificar perfiles profesionales (Sprint 5, si hay capacidad) | B38: 1.5 | D38: 1 | E38: 9 | F38: 2 | G38: 2 | H38: 2 | L38: E7 Reservas | M38: =SUM(C54:C55)*$M$6+SUM(D54:D55)*$M$7+SUM(E54:E55)*$M$8+SUM(F54:F55)*$M$9+SUM(G54:G55)*$M$10+SUM(H54:H55)*$M$11
A39: FS-HU-23 Profesionales favoritos (Sprint 3) | B39: 1.5 | D39: 1 | E39: 9 | F39: 2 | G39: 2 | H39: 2 | L39: TOTAL CODIFICACION | M39: =SUM(M32:M38)
A40: FS-HU-24 Calificar y reseñar profesionales (Sprint 3) | B40: 2 | D40: 1 | E40: 15 | F40: 4 | G40: 4 | H40: 3
A41: E3 Búsqueda geolocalizada
A42: FS-HU-05 Buscar cerca de mí (Sprint 3) | B42: 3.5 | D42: 2 | E42: 24 | F42: 6 | G42: 7 | H42: 4
A43: FS-HU-06 Vista de mapa y lista (Sprint 3) | B43: 2 | D43: 3 | E43: 16 | F43: 1 | G43: 5 | H43: 2
A44: FS-HU-22 Búsqueda avanzada de profesionales (Sprint 3) | B44: 2 | D44: 1 | E44: 15 | F44: 4 | G44: 4 | H44: 3
A45: E4 Asistente de inteligencia artificial
A46: FS-HU-07 Chat de orientación (Sprint 4) | B46: 3.5 | D46: 4 | E46: 26 | F46: 2 | G46: 9 | H46: 2
A47: FS-HU-08 Recomendación de profesional (Sprint 4) | B47: 2 | D47: 3 | E47: 16 | F47: 1 | G47: 5 | H47: 2
A48: E5 Gestor de alimentación
A49: FS-HU-09 Registro por lenguaje natural (Sprint 5) | B49: 3.5 | D49: 4 | E49: 26 | F49: 2 | G49: 9 | H49: 2
A50: FS-HU-10 Seguimiento de calorías (Sprint 5) | B50: 2 | D50: 1 | E50: 15 | F50: 4 | G50: 4 | H50: 3
A51: E6 Infraestructura
A52: FS-HU-11 Dockerización (Sprint 5) | B52: 1.5 | E52: 8 | F52: 4 | G52: 4
A53: E7 Reservas
A54: FS-HU-13 Disponibilidad del profesional (Sprint 2) | B54: 2 | D54: 1 | E54: 15 | F54: 4 | G54: 4 | H54: 3
A55: FS-HU-14 Reservar hora (Sprint 3) | B55: 3.5 | D55: 2 | E55: 24 | F55: 6 | G55: 7 | H55: 4
A56: Fase Implementación y Cierre (semanas 15 a 18) | B56: Días | C56: JP | D56: AF | E56: PG | F56: DBA | G56: TS | H56: DI
A57: Pruebas de integración con MySQL real y ejecución de los casos de prueba manuales | B57: 1.5 | E57: 4 | G57: 16
A58: Pruebas de seguridad (npm audit, validación de entradas, OWASP) y de rendimiento (carga básica) | B58: 1 | E58: 4 | F58: 1 | G58: 8
A59: Corrección de defectos (Registro de Defectos) | B59: 0.5 | E59: 6 | G59: 2
A60: Plan de Pruebas con evidencias (semana 15) | B60: 0.5 | D60: 2 | G60: 6
A61: Despliegue con docker-compose y Manual técnico y de despliegue | B61: 1 | C61: 1 | E61: 6 | F61: 2
A62: Informe final y presentación del proyecto (Fase 3) | B62: 1.5 | C62: 6 | D62: 6 | E62: 3 | H62: 3
A63: Cierre del proyecto (retrospectiva final y entrega de evidencias) | B63: 0.5 | C63: 2 | D63: 1 | E63: 1
B64: Días | C64: JP | D64: AF | E64: PG | F64: DBA | G64: TS | H64: DI
A65: Total | B65: =SUM(B6:B63) | C65: =SUM(C6:C63) | D65: =SUM(D6:D63) | E65: =SUM(E6:E63) | F65: =SUM(F6:F63) | G65: =SUM(G6:G63) | H65: =SUM(H6:H63)
A67: Supuestos de la estimación (actualizada al 03-10-2026)
A68: 1. Las horas de FS-HU-01 y FS-HU-02 son las reales del Sprint 1 (43 h registradas en el Sprint Backlog). Las demás historias se estiman con la misma relación: 5,4 h por punto de historia (43 h / 8 puntos), es decir, 2 puntos = 11 h, 3 puntos = 16 h, 5 puntos = 27 h y 8 puntos = 43 h.
A69: 2. Las horas de cada historia se reparten por rol según su tipo: con tablas nuevas (base de datos, API y pantallas), de interfaz (más horas de diseño) o de integración externa e IA (más análisis y pruebas).
A70: 3. Los puntos de FS-HU-21 a FS-HU-24 son los propuestos (5, 5, 3 y 5), a confirmar en la planificación del Sprint 3. La iteración de cada historia es la del Product Backlog.
A71: 4. Días = días de trabajo efectivo del equipo (12 h por día: 3 integrantes x 4 h), redondeados a medio día. No son días calendario: las actividades se ejecutan en paralelo dentro de cada sprint, según la Carta Gantt.
A72: 5. Un integrante puede cumplir varios roles. El costo se obtiene valorizando las horas de cada rol con su valor HH (hoja ANALISIS INGRESOS, sueldo / 180 h mensuales).
A73: 6. Las horas de las fases de análisis, diseño e implementación y cierre son estimaciones: no hay registro de horas reales de la Fase 1, y las horas reales de cada sprint se registran en su Sprint Backlog y burndown.

Sheet ANALISIS INGRESOS
H2: FUENTE DE INFORMACION www.mifuturo.cl / www.universia.cl
H3: INGENIERIA INFORMÁTICA
C4: EXPERIENCIA
A5: SIGLA | B5: ROL | C5: (- 2 años) | D5: (+2 años) | E5: RESPONS. | F5: SUELDO | G5: HH
A6: JP | B6: Jefe de Proyecto | D6: x | E6: 0.5 | F6: =(C20*E6)+1300000 | G6: =F6/180
A7: AF | B7: Analista Funcional | D7: x | E7: 0.3 | F7: =(C22*E7)+1300000 | G7: =F7/180
A8: PG | B8: Programador | C8: x | F8: =B19 | G8: =F8/180
A9: DBA | B9: Desarrollador BD | C9: x | E9: 0.3 | F9: =(B19*E9)+500000 | G9: =F9/180
A10: TS | B10: Testing | C10: x | F10: =B19 | G10: =F10/180
A11: DI | B11: Diseñador | C11: x | F11: 500000 | G11: =F11/180
A12: El valor HH de cada rol (columna G, sueldo / 180 h mensuales) alimenta la columna COSTO x HORA del diccionario de la hoja EDT.
D14: Hrs.Sem. | E14: 45
D15: HRS.Mens. | E15: =E14*4
D16: HH | E16: Sueldo/180hrs
A18: PROMEDIO | B18: PROGRAMADOR | C18: INGENIERO | D18: DISEÑADOR
A19: Ingreso Primer Año | B19: 500000 | C19: 700000 | D19: 500000
A20: Ingreso Experiencia | B20: 900000 | C20: 1300000 | D20: 800000
H23: ANALISTA PROGRAMADOR
H42: DISEÑADOR
